yesilfilm/__init__.py
yesilfilm/main.py
yesilfilm-0.1.dist-info/METADATA
yesilfilm-0.1.dist-info/WHEEL
yesilfilm-0.1.dist-info/entry_points.txt
yesilfilm-0.1.dist-info/top_level.txt
yesilfilm-0.1.dist-info/RECORD
