Metadata-Version: 2.1
Name: yesilfilm
Version: 0.1
Summary: Yeşilçam filmleri seçme ve oynatma uygulaması.
Home-page: https://github.com/Handsomeskull/yesilfilm.git
Author: Dogukan
Author-email: nagamiisbruh@gmail.com
Classifier: Programming Language :: Python :: 3
Classifier: License :: OSI Approved :: MIT License
Classifier: Operating System :: OS Independent
Requires-Python: >=3.6
